setup.cfg
setup.py
decbin/__init__.py
decbin/decbin.py
decbin.egg-info/PKG-INFO
decbin.egg-info/SOURCES.txt
decbin.egg-info/dependency_links.txt
decbin.egg-info/not-zip-safe
decbin.egg-info/top_level.txt