Metadata-Version: 1.0
Name: decbin
Version: 0.0.1
Summary: Simple library to covert binary to decimal and decimal to binary
Home-page: UNKNOWN
Author: UNKNOWN
Author-email: asimonov1998@gmail.com
License: UNKNOWN
Platform: UNKNOWN
